Face_Simiarity/__init__.py
Face_Simiarity/similarity.py
face_similarity-0.1.dist-info/METADATA
face_similarity-0.1.dist-info/WHEEL
face_similarity-0.1.dist-info/top_level.txt
face_similarity-0.1.dist-info/RECORD
