Metadata-Version: 2.1
Name: face-similarity
Version: 0.1
Summary: A package to compare face similarity from documents and original image.
Home-page: https://github.com/yourusername/face_similarity
Author: Muhammad Furqan Javed
Author-email: mfurqanjaved@gmail.com
Classifier: Programming Language :: Python :: 3
Classifier: License :: OSI Approved :: MIT License
Classifier: Operating System :: OS Independent
Requires-Python: >=3.6
Requires-Dist: opencv-python
Requires-Dist: numpy
Requires-Dist: scikit-image
Requires-Dist: scikit-learn
Requires-Dist: face-recognition
